setup.py
logworm/__init__.py
logworm/core.py
logworm/version.py
logworm.egg-info/PKG-INFO
logworm.egg-info/SOURCES.txt
logworm.egg-info/dependency_links.txt
logworm.egg-info/top_level.txt