Metadata-Version: 1.1
Name: logworm
Version: 0.0.6
Summary: Streamlike handler for process output.
Home-page: https://github.com/smaragden/logworm
Author: Fredrik Brannbacka
Author-email: fredrik@burnhill.se
License: Apache 2.0
Platform: UNKNOWN
Classifier: Development Status :: 2 - Pre-Alpha
Classifier: Environment :: No Input/Output (Daemon)
Classifier: Environment :: Console
Classifier: Environment :: MacOS X
Classifier: Intended Audience :: End Users/Desktop
Classifier: Intended Audience :: System Administrators
Classifier: Operating System :: MacOS :: MacOS X
Classifier: Operating System :: POSIX :: Linux
Classifier: Programming Language :: Python
Classifier: Programming Language :: Python :: 2
Classifier: Programming Language :: Python :: 2.7
Classifier: Topic :: System :: Systems Administration
